[
  {
    "s": "DA",
    "p": [
      24,
      3
    ]
  },
  {
    "s": "DAR",
    "p": [
      33,
      23,
      27,
      16,
      6
    ]
  },
  {
    "s": "DATO",
    "p": [
      24,
      23,
      20,
      18,
      16
    ]
  },
  {
    "s": "DATOS",
    "p": [
      27,
      23,
      18,
      16,
      4,
      31,
      8,
      29,
      25,
      24,
      21,
      14,
      3,
      2
    ]
  },
  {
    "s": "DAVID17",
    "p": [
      1
    ]
  },
  {
    "s": "DE",
    "p": [
      4,
      30,
      24,
      32,
      33,
      23,
      21,
      22,
      2,
      27,
      15,
      14,
      6,
      36,
      28,
      20,
      19,
      35,
      29,
      16,
      31,
      26,
      18,
      34,
      8,
      17,
      1,
      25,
      12,
      13,
      11,
      5,
      9,
      7,
      3,
      10
    ]
  },
  {
    "s": "DEBE",
    "p": [
      33,
      30,
      31,
      27,
      26,
      24,
      22,
      18,
      16,
      2
    ]
  },
  {
    "s": "DEBER",
    "p": [
      24,
      23,
      2
    ]
  },
  {
    "s": "DEBERÁ",
    "p": [
      15,
      22,
      35,
      27,
      23,
      4
    ]
  },
  {
    "s": "DECIR",
    "p": [
      31,
      27,
      23,
      2
    ]
  },
  {
    "s": "DEFINITIVO",
    "p": [
      30
    ]
  },
  {
    "s": "DEJA",
    "p": [
      23
    ]
  },
  {
    "s": "DEJAR",
    "p": [
      24
    ]
  },
  {
    "s": "DEL",
    "p": [
      32,
      28,
      30,
      24,
      36,
      26,
      20,
      19,
      15,
      13,
      12,
      3,
      29,
      25,
      6,
      31,
      23,
      22,
      18,
      16,
      8,
      7,
      5,
      1
    ]
  },
  {
    "s": "DENTRO",
    "p": [
      29,
      21
    ]
  },
  {
    "s": "DEPARTAMENTO",
    "p": [
      26
    ]
  },
  {
    "s": "DEPENDIENDO",
    "p": [
      27
    ]
  },
  {
    "s": "DESARROLLADOR",
    "p": [
      36,
      12,
      6
    ]
  },
  {
    "s": "DESCRIPCIÓN",
    "p": [
      32,
      30,
      28,
      26,
      2
    ]
  },
  {
    "s": "DESDE",
    "p": [
      33,
      35,
      34,
      25,
      21
    ]
  },
  {
    "s": "DESEA",
    "p": [
      31,
      27,
      4,
      33,
      24,
      23,
      18,
      16
    ]
  },
  {
    "s": "DESEADO",
    "p": [
      31
    ]
  },
  {
    "s": "DESHABILITA",
    "p": [
      35,
      34
    ]
  },
  {
    "s": "DESHABILITADO",
    "p": [
      24
    ]
  },
  {
    "s": "DESHABILITADOS",
    "p": [
      24,
      19
    ]
  },
  {
    "s": "DESPLEGABLE",
    "p": [
      24,
      22,
      19,
      32,
      30,
      28,
      27,
      26,
      23
    ]
  },
  {
    "s": "DETERMINADO",
    "p": [
      16
    ]
  },
  {
    "s": "DICHA",
    "p": [
      33
    ]
  },
  {
    "s": "DICHO",
    "p": [
      21,
      2
    ]
  },
  {
    "s": "DIFERENCIA",
    "p": [
      32
    ]
  },
  {
    "s": "DIFERENTE",
    "p": [
      32
    ]
  },
  {
    "s": "DIFERENTES",
    "p": [
      6
    ]
  },
  {
    "s": "DINAMICAS",
    "p": [
      27,
      23
    ]
  },
  {
    "s": "DINÁMICAS",
    "p": [
      31
    ]
  },
  {
    "s": "DIO",
    "p": [
      32
    ]
  },
  {
    "s": "DIRECTAMENTE",
    "p": [
      29,
      25
    ]
  },
  {
    "s": "DIRECTOR",
    "p": [
      28,
      26
    ]
  },
  {
    "s": "DIRECTOS",
    "p": [
      12,
      11,
      10,
      9,
      8
    ]
  },
  {
    "s": "DIRIGIDO",
    "p": [
      25
    ]
  },
  {
    "s": "DOBLE",
    "p": [
      27,
      31,
      23,
      18,
      16
    ]
  },
  {
    "s": "DONDE",
    "p": [
      8,
      10,
      31,
      32,
      30,
      29,
      28,
      27,
      24,
      20,
      19,
      13,
      11,
      9,
      5,
      3,
      2
    ]
  },
  {
    "s": "DOS",
    "p": [
      33,
      21,
      6,
      36,
      31,
      30,
      29,
      25,
      14,
      7,
      5
    ]
  },
  {
    "s": "DÍAS",
    "p": [
      30,
      32
    ]
  }
]